Metadata-Version: 2.0
Name: iter2
Version: 1.1
Summary: Implementation of some rich-iterator concept
Home-page: https://github.com/ramon93i7/iter2
Author: Shemyakin Roman
Author-email: ramon93i7@gmail.com
License: MIT
Platform: UNKNOWN
Classifier: Programming Language :: Python :: 3
Classifier: Intended Audience :: Developers
Classifier: Topic :: Software Development :: Libraries
Classifier: License :: OSI Approved :: MIT License
